growingio_tracker/__init__.py
growingio_tracker/async_buffered_consumer.py
growingio_tracker/buffered_consumer.py
growingio_tracker/consumer.py
growingio_tracker/data_parser.py
growingio_tracker/debug_consumer.py
growingio_tracker/default_consumer.py
growingio_tracker/message.py
growingio_tracker/version.py
growingio_tracker_protobuf/__init__.py
growingio_tracker_protobuf/event_v3_pb2.py
growingio_tracker_protobuf/protobuf_parser.py
growingio_tracker_snappy/__init__.py
growingio_tracker_snappy/snappy_parser.py
growingio_tracker-1.0.5.dist-info/LICENSE.txt
growingio_tracker-1.0.5.dist-info/METADATA
growingio_tracker-1.0.5.dist-info/WHEEL
growingio_tracker-1.0.5.dist-info/top_level.txt
growingio_tracker-1.0.5.dist-info/RECORD
