Metadata-Version: 2.1
Name: growingio-tracker
Version: 1.0.5
Summary: GrowingIO Tracker library for Python
Home-page: https://github.com/growingio/growingio-python-sdk-v3/
Author: cpacm,GrowingIO SDK Team
Author-email: sdk-integration@growingio.com
License: Apache
Keywords: growingio python analytics
Classifier: License :: OSI Approved :: Apache Software License
Classifier: Operating System :: OS Independent
Classifier: Programming Language :: Python :: 2
Classifier: Programming Language :: Python :: 2.7
Classifier: Programming Language :: Python :: 3
Classifier: Programming Language :: Python :: 3.5
Classifier: Programming Language :: Python :: 3.6
Classifier: Programming Language :: Python :: 3.7
Classifier: Programming Language :: Python :: 3.8
Classifier: Programming Language :: Python :: 3.9
Classifier: Programming Language :: Python :: 3.10
Requires-Python: >=2.7, !=3.4.*
License-File: LICENSE.txt
Requires-Dist: six >=1.9.0
Requires-Dist: requests >=2.25
Requires-Dist: urllib3 >=1.26
